<?xml version='1.0' encoding='ISO-8859-1'?>
<?xml-stylesheet type='text/xsl' href='image_metadata_stylesheet.xsl'?>
<dataset>
<name>Training faces</name>
<comment>These are images from the PASCAL VOC 2011 dataset.</comment>
<images>
  <image file='0.jpg'> 
    <box top='90' left='194' width='37' height='37'/>
    <box top='114' left='158' width='37' height='37'/>
    <box top='89' left='381' width='45' height='44'/>
    <box top='198' left='94' width='37' height='37'/>
    <box top='214' left='178' width='37' height='37'/>
    <box top='86' left='294' width='37' height='37'/>
    <box top='233' left='309' width='45' height='44'/>
  </image>
  
</images>
</dataset>